[{"Date":"11/13/2021","Transaction":-1,"Value":256500,"Symbol":"PGR"},{"Date":"11/10/2021","Transaction":1,"Value":101175,"Symbol":"HMN"},{"Date":"11/10/2021","Transaction":-1,"Value":3000229,"Symbol":"CB"},{"Date":"11/10/2021","Transaction":0,"Value":677215,"Symbol":"AFG"},{"Date":"11/10/2021","Transaction":-1,"Value":2321976,"Symbol":"AFG"},{"Date":"11/10/2021","Transaction":-1,"Value":140565,"Symbol":"PLMR"},{"Date":"11/09/2021","Transaction":0,"Value":87726,"Symbol":"STFC"},{"Date":"11/09/2021","Transaction":-1,"Value":204505,"Symbol":"STFC"},{"Date":"11/09/2021","Transaction":0,"Value":1679950,"Symbol":"L"},{"Date":"11/09/2021","Transaction":-1,"Value":505657,"Symbol":"L"},{"Date":"11/09/2021","Transaction":-1,"Value":1813032,"Symbol":"SIGI"},{"Date":"11/09/2021","Transaction":-1,"Value":23974,"Symbol":"NMIH"},{"Date":"11/09/2021","Transaction":0,"Value":99942,"Symbol":"AFG"},{"Date":"11/08/2021","Transaction":1,"Value":149704,"Symbol":"PLMR"},{"Date":"11/04/2021","Transaction":-1,"Value":1004286,"Symbol":"KNSL"},{"Date":"11/04/2021","Transaction":-1,"Value":502207,"Symbol":"KNSL"},{"Date":"11/03/2021","Transaction":0,"Value":1325,"Symbol":"LMND"},{"Date":"11/03/2021","Transaction":-1,"Value":36000,"Symbol":"LMND"},{"Date":"11/03/2021","Transaction":-1,"Value":1124000,"Symbol":"LMND"},{"Date":"11/03/2021","Transaction":-1,"Value":432886,"Symbol":"SIGI"},{"Date":"11/03/2021","Transaction":-1,"Value":625344,"Symbol":"SIGI"},{"Date":"11/02/2021","Transaction":-1,"Value":504675,"Symbol":"CNA"},{"Date":"11/01/2021","Transaction":-1,"Value":319500,"Symbol":"LMND"},{"Date":"11/01/2021","Transaction":0,"Value":1167729,"Symbol":"TRV"},{"Date":"11/01/2021","Transaction":-1,"Value":2379618,"Symbol":"TRV"},{"Date":"10/29/2021","Transaction":0,"Value":480007,"Symbol":"CINF"},{"Date":"10/29/2021","Transaction":-1,"Value":6091297,"Symbol":"CB"},{"Date":"10/26/2021","Transaction":-1,"Value":166842,"Symbol":"TRV"},{"Date":"10/25/2021","Transaction":0,"Value":623091,"Symbol":"TRV"},{"Date":"10/25/2021","Transaction":-1,"Value":950185,"Symbol":"TRV"},{"Date":"10/21/2021","Transaction":-1,"Value":318237,"Symbol":"PGR"},{"Date":"10/20/2021","Transaction":-1,"Value":605663,"Symbol":"PLMR"},{"Date":"10/18/2021","Transaction":-1,"Value":324850,"Symbol":"LMND"},{"Date":"10/18/2021","Transaction":-1,"Value":948640,"Symbol":"PLMR"},{"Date":"10/14/2021","Transaction":-1,"Value":208568,"Symbol":"PGR"},{"Date":"10/11/2021","Transaction":-1,"Value":21656,"Symbol":"HMN"},{"Date":"10/06/2021","Transaction":-1,"Value":118215,"Symbol":"PLMR"},{"Date":"10/05/2021","Transaction":0,"Value":0,"Symbol":"ALL"},{"Date":"10/01/2021","Transaction":-1,"Value":606461,"Symbol":"PLMR"},{"Date":"10/01/2021","Transaction":-1,"Value":258014,"Symbol":"UVE"},{"Date":"09/29/2021","Transaction":-1,"Value":40370,"Symbol":"HMN"},{"Date":"09/28/2021","Transaction":1,"Value":88000,"Symbol":"UIHC"},{"Date":"09/27/2021","Transaction":1,"Value":36600,"Symbol":"UIHC"},{"Date":"09/24/2021","Transaction":-1,"Value":133320,"Symbol":"HMN"},{"Date":"09/23/2021","Transaction":1,"Value":8843,"Symbol":"HRTG"},{"Date":"09/23/2021","Transaction":1,"Value":74368,"Symbol":"UIHC"},{"Date":"09/22/2021","Transaction":1,"Value":25275,"Symbol":"UIHC"},{"Date":"09/22/2021","Transaction":1,"Value":51440,"Symbol":"UIHC"},{"Date":"09/22/2021","Transaction":-1,"Value":551628,"Symbol":"PLMR"},{"Date":"09/21/2021","Transaction":1,"Value":116971,"Symbol":"UIHC"},{"Date":"09/21/2021","Transaction":1,"Value":94383,"Symbol":"UIHC"},{"Date":"09/21/2021","Transaction":-1,"Value":213513,"Symbol":"PGR"},{"Date":"09/20/2021","Transaction":1,"Value":220486,"Symbol":"UIHC"},{"Date":"09/18/2021","Transaction":0,"Value":0,"Symbol":"UIHC"},{"Date":"09/18/2021","Transaction":0,"Value":0,"Symbol":"UIHC"},{"Date":"09/17/2021","Transaction":1,"Value":17040,"Symbol":"HRTG"},{"Date":"09/17/2021","Transaction":1,"Value":58400,"Symbol":"HRTG"},{"Date":"09/17/2021","Transaction":-1,"Value":4166793,"Symbol":"PGR"},{"Date":"09/16/2021","Transaction":1,"Value":49738,"Symbol":"HRTG"},{"Date":"09/16/2021","Transaction":-1,"Value":483779,"Symbol":"AFG"},{"Date":"09/16/2021","Transaction":-1,"Value":1024198,"Symbol":"PLMR"},{"Date":"09/15/2021","Transaction":1,"Value":1096,"Symbol":"UIHC"},{"Date":"09/15/2021","Transaction":1,"Value":44037,"Symbol":"UIHC"},{"Date":"09/15/2021","Transaction":0,"Value":22500,"Symbol":"PLMR"},{"Date":"09/15/2021","Transaction":-1,"Value":163609,"Symbol":"PLMR"},{"Date":"09/14/2021","Transaction":0,"Value":369308,"Symbol":"AFG"},{"Date":"09/10/2021","Transaction":-1,"Value":768200,"Symbol":"LMND"},{"Date":"09/09/2021","Transaction":1,"Value":99250,"Symbol":"KMPR"},{"Date":"09/08/2021","Transaction":0,"Value":0,"Symbol":"PLMR"},{"Date":"09/08/2021","Transaction":0,"Value":0,"Symbol":"PLMR"},{"Date":"09/08/2021","Transaction":0,"Value":0,"Symbol":"PLMR"},{"Date":"09/08/2021","Transaction":0,"Value":0,"Symbol":"PLMR"},{"Date":"09/08/2021","Transaction":0,"Value":0,"Symbol":"PLMR"},{"Date":"09/08/2021","Transaction":0,"Value":0,"Symbol":"PLMR"},{"Date":"09/08/2021","Transaction":0,"Value":0,"Symbol":"PLMR"},{"Date":"09/08/2021","Transaction":-1,"Value":130755,"Symbol":"PLMR"},{"Date":"09/07/2021","Transaction":1,"Value":8786,"Symbol":"MCY"},{"Date":"09/07/2021","Transaction":-1,"Value":959992,"Symbol":"CB"},{"Date":"09/02/2021","Transaction":-1,"Value":76368,"Symbol":"STFC"},{"Date":"09/01/2021","Transaction":0,"Value":1325,"Symbol":"LMND"},{"Date":"09/01/2021","Transaction":-1,"Value":39120,"Symbol":"LMND"},{"Date":"09/01/2021","Transaction":0,"Value":52560,"Symbol":"L"},{"Date":"09/01/2021","Transaction":0,"Value":52560,"Symbol":"L"},{"Date":"09/01/2021","Transaction":0,"Value":52560,"Symbol":"L"},{"Date":"09/01/2021","Transaction":0,"Value":52560,"Symbol":"L"},{"Date":"09/01/2021","Transaction":0,"Value":52560,"Symbol":"L"},{"Date":"09/01/2021","Transaction":0,"Value":52560,"Symbol":"L"},{"Date":"09/01/2021","Transaction":-1,"Value":31203,"Symbol":"L"},{"Date":"09/01/2021","Transaction":-1,"Value":31203,"Symbol":"L"},{"Date":"09/01/2021","Transaction":-1,"Value":31203,"Symbol":"L"},{"Date":"09/01/2021","Transaction":-1,"Value":31208,"Symbol":"L"},{"Date":"09/01/2021","Transaction":-1,"Value":15574,"Symbol":"L"},{"Date":"09/01/2021","Transaction":-1,"Value":31203,"Symbol":"L"},{"Date":"09/01/2021","Transaction":-1,"Value":278276,"Symbol":"UVE"},{"Date":"08/31/2021","Transaction":-1,"Value":1040199,"Symbol":"STFC"},{"Date":"08/31/2021","Transaction":-1,"Value":5577729,"Symbol":"CB"},{"Date":"08/31/2021","Transaction":-1,"Value":689300,"Symbol":"AFG"},{"Date":"08/30/2021","Transaction":-1,"Value":1328750,"Symbol":"CB"},{"Date":"08/30/2021","Transaction":0,"Value":602691,"Symbol":"AFG"},{"Date":"08/30/2021","Transaction":-1,"Value":2055683,"Symbol":"AFG"},{"Date":"08/27/2021","Transaction":0,"Value":456016,"Symbol":"STFC"},{"Date":"08/27/2021","Transaction":0,"Value":155538,"Symbol":"STFC"},{"Date":"08/27/2021","Transaction":-1,"Value":539221,"Symbol":"STFC"},{"Date":"08/27/2021","Transaction":-1,"Value":1030362,"Symbol":"STFC"},{"Date":"08/27/2021","Transaction":0,"Value":2464135,"Symbol":"TRV"},{"Date":"08/27/2021","Transaction":-1,"Value":3376392,"Symbol":"TRV"},{"Date":"08/26/2021","Transaction":0,"Value":56117,"Symbol":"CINF"},{"Date":"08/26/2021","Transaction":0,"Value":454393,"Symbol":"STFC"},{"Date":"08/26/2021","Transaction":-1,"Value":1369339,"Symbol":"STFC"},{"Date":"08/25/2021","Transaction":0,"Value":614578,"Symbol":"STFC"},{"Date":"08/25/2021","Transaction":-1,"Value":1831295,"Symbol":"STFC"},{"Date":"08/24/2021","Transaction":0,"Value":3332511,"Symbol":"CB"},{"Date":"08/24/2021","Transaction":-1,"Value":8446449,"Symbol":"CB"},{"Date":"08/23/2021","Transaction":0,"Value":5242471,"Symbol":"CB"},{"Date":"08/23/2021","Transaction":-1,"Value":5598300,"Symbol":"CB"},{"Date":"08/23/2021","Transaction":-1,"Value":13055861,"Symbol":"CB"},{"Date":"08/20/2021","Transaction":-1,"Value":50086,"Symbol":"CNA"},{"Date":"08/20/2021","Transaction":0,"Value":315302,"Symbol":"STFC"},{"Date":"08/20/2021","Transaction":-1,"Value":828140,"Symbol":"STFC"},{"Date":"08/20/2021","Transaction":0,"Value":80000,"Symbol":"KNSL"},{"Date":"08/20/2021","Transaction":-1,"Value":918600,"Symbol":"KNSL"},{"Date":"08/20/2021","Transaction":0,"Value":591605,"Symbol":"TRV"},{"Date":"08/20/2021","Transaction":-1,"Value":1604732,"Symbol":"TRV"},{"Date":"08/20/2021","Transaction":-1,"Value":139808,"Symbol":"THG"},{"Date":"08/19/2021","Transaction":-1,"Value":607000,"Symbol":"PGR"},{"Date":"08/19/2021","Transaction":-1,"Value":1145640,"Symbol":"PGR"},{"Date":"08/19/2021","Transaction":-1,"Value":1371173,"Symbol":"PGR"},{"Date":"08/19/2021","Transaction":-1,"Value":1154414,"Symbol":"PGR"},{"Date":"08/18/2021","Transaction":1,"Value":6760,"Symbol":"HRTG"},{"Date":"08/18/2021","Transaction":-1,"Value":548173,"Symbol":"CB"},{"Date":"08/18/2021","Transaction":-1,"Value":31396,"Symbol":"PLMR"},{"Date":"08/18/2021","Transaction":-1,"Value":522139,"Symbol":"PLMR"},{"Date":"08/16/2021","Transaction":-1,"Value":134615,"Symbol":"HMN"},{"Date":"08/16/2021","Transaction":0,"Value":302792,"Symbol":"STFC"},{"Date":"08/16/2021","Transaction":-1,"Value":805000,"Symbol":"STFC"},{"Date":"08/13/2021","Transaction":0,"Value":64000,"Symbol":"KNSL"},{"Date":"08/13/2021","Transaction":-1,"Value":724840,"Symbol":"KNSL"},{"Date":"08/13/2021","Transaction":0,"Value":210070,"Symbol":"AFG"},{"Date":"08/13/2021","Transaction":-1,"Value":943214,"Symbol":"AFG"},{"Date":"08/12/2021","Transaction":0,"Value":528086,"Symbol":"AFG"},{"Date":"08/12/2021","Transaction":-1,"Value":1946791,"Symbol":"AFG"},{"Date":"08/11/2021","Transaction":1,"Value":16750,"Symbol":"KMPR"},{"Date":"08/11/2021","Transaction":0,"Value":743769,"Symbol":"CB"},{"Date":"08/11/2021","Transaction":-1,"Value":660358,"Symbol":"CB"},{"Date":"08/11/2021","Transaction":-1,"Value":1825200,"Symbol":"CB"},{"Date":"08/11/2021","Transaction":0,"Value":1779862,"Symbol":"L"},{"Date":"08/11/2021","Transaction":-1,"Value":719299,"Symbol":"L"},{"Date":"08/11/2021","Transaction":1,"Value":159,"Symbol":"UIHC"},{"Date":"08/11/2021","Transaction":0,"Value":273050,"Symbol":"THG"},{"Date":"08/11/2021","Transaction":-1,"Value":703425,"Symbol":"THG"},{"Date":"08/11/2021","Transaction":-1,"Value":129090,"Symbol":"PLMR"},{"Date":"08/10/2021","Transaction":0,"Value":1353938,"Symbol":"L"},{"Date":"08/10/2021","Transaction":-1,"Value":509263,"Symbol":"L"},{"Date":"08/09/2021","Transaction":1,"Value":49749,"Symbol":"CINF"},{"Date":"08/09/2021","Transaction":-1,"Value":931123,"Symbol":"KNSL"},{"Date":"08/09/2021","Transaction":-1,"Value":465446,"Symbol":"KNSL"},{"Date":"08/09/2021","Transaction":0,"Value":164668,"Symbol":"AFG"},{"Date":"08/09/2021","Transaction":-1,"Value":413476,"Symbol":"AFG"},{"Date":"08/09/2021","Transaction":0,"Value":173300,"Symbol":"THG"},{"Date":"08/09/2021","Transaction":-1,"Value":690000,"Symbol":"THG"},{"Date":"08/06/2021","Transaction":1,"Value":16340,"Symbol":"KMPR"},{"Date":"08/06/2021","Transaction":0,"Value":90030,"Symbol":"AFG"},{"Date":"08/06/2021","Transaction":-1,"Value":976166,"Symbol":"AFG"},{"Date":"08/06/2021","Transaction":-1,"Value":396670,"Symbol":"AFG"},{"Date":"08/06/2021","Transaction":0,"Value":136525,"Symbol":"THG"},{"Date":"08/06/2021","Transaction":0,"Value":231667,"Symbol":"THG"},{"Date":"08/06/2021","Transaction":-1,"Value":909420,"Symbol":"THG"},{"Date":"08/06/2021","Transaction":-1,"Value":343358,"Symbol":"THG"},{"Date":"08/05/2021","Transaction":0,"Value":270090,"Symbol":"AFG"},{"Date":"08/05/2021","Transaction":-1,"Value":1179932,"Symbol":"AFG"},{"Date":"08/05/2021","Transaction":-1,"Value":68000,"Symbol":"PLMR"},{"Date":"08/04/2021","Transaction":1,"Value":1540570,"Symbol":"KMPR"},{"Date":"08/02/2021","Transaction":0,"Value":1988,"Symbol":"LMND"},{"Date":"08/02/2021","Transaction":-1,"Value":66505,"Symbol":"LMND"},{"Date":"08/02/2021","Transaction":0,"Value":460642,"Symbol":"THG"},{"Date":"08/02/2021","Transaction":-1,"Value":756496,"Symbol":"THG"},{"Date":"08/02/2021","Transaction":-1,"Value":280094,"Symbol":"UVE"},{"Date":"07/30/2021","Transaction":-1,"Value":399960,"Symbol":"HMN"},{"Date":"07/30/2021","Transaction":-1,"Value":2004652,"Symbol":"SIGI"},{"Date":"07/30/2021","Transaction":0,"Value":520802,"Symbol":"THG"},{"Date":"07/30/2021","Transaction":-1,"Value":828056,"Symbol":"THG"},{"Date":"07/26/2021","Transaction":1,"Value":14376,"Symbol":"RLI"},{"Date":"07/26/2021","Transaction":0,"Value":1272480,"Symbol":"TRV"},{"Date":"07/26/2021","Transaction":-1,"Value":1790680,"Symbol":"TRV"},{"Date":"07/21/2021","Transaction":-1,"Value":503340,"Symbol":"PLMR"},{"Date":"07/21/2021","Transaction":-1,"Value":46408,"Symbol":"PLMR"},{"Date":"07/20/2021","Transaction":0,"Value":0,"Symbol":"PGR"},{"Date":"07/19/2021","Transaction":-1,"Value":869617,"Symbol":"PGR"},{"Date":"07/19/2021","Transaction":-1,"Value":905731,"Symbol":"PGR"},{"Date":"07/19/2021","Transaction":-1,"Value":295018,"Symbol":"PGR"},{"Date":"07/15/2021","Transaction":-1,"Value":1086480,"Symbol":"PGR"},{"Date":"07/07/2021","Transaction":-1,"Value":114960,"Symbol":"PLMR"},{"Date":"07/01/2021","Transaction":-1,"Value":573333,"Symbol":"PLMR"},{"Date":"07/01/2021","Transaction":-1,"Value":277026,"Symbol":"UVE"},{"Date":"06/30/2021","Transaction":0,"Value":22500,"Symbol":"PLMR"},{"Date":"06/30/2021","Transaction":-1,"Value":158701,"Symbol":"PLMR"},{"Date":"06/25/2021","Transaction":-1,"Value":333050,"Symbol":"AFG"},{"Date":"06/23/2021","Transaction":-1,"Value":506338,"Symbol":"PLMR"},{"Date":"06/21/2021","Transaction":0,"Value":1392000,"Symbol":"ALL"},{"Date":"06/21/2021","Transaction":-1,"Value":1917570,"Symbol":"ALL"},{"Date":"06/17/2021","Transaction":-1,"Value":4129906,"Symbol":"PGR"},{"Date":"06/17/2021","Transaction":-1,"Value":1114320,"Symbol":"PGR"},{"Date":"06/16/2021","Transaction":-1,"Value":110330,"Symbol":"CNA"},{"Date":"06/09/2021","Transaction":-1,"Value":224970,"Symbol":"SIGI"},{"Date":"06/09/2021","Transaction":-1,"Value":113953,"Symbol":"PLMR"},{"Date":"06/09/2021","Transaction":-1,"Value":280610,"Symbol":"UVE"},{"Date":"06/08/2021","Transaction":-1,"Value":1035370,"Symbol":"LMND"},{"Date":"06/08/2021","Transaction":-1,"Value":15984,"Symbol":"AFG"},{"Date":"06/07/2021","Transaction":-1,"Value":966389,"Symbol":"LMND"},{"Date":"06/04/2021","Transaction":-1,"Value":561528,"Symbol":"AFG"},{"Date":"06/03/2021","Transaction":-1,"Value":279187,"Symbol":"KNSL"},{"Date":"06/02/2021","Transaction":-1,"Value":219643,"Symbol":"AFG"},{"Date":"06/01/2021","Transaction":0,"Value":0,"Symbol":"ALL"},{"Date":"06/01/2021","Transaction":0,"Value":0,"Symbol":"ALL"},{"Date":"06/01/2021","Transaction":0,"Value":0,"Symbol":"ALL"},{"Date":"06/01/2021","Transaction":0,"Value":0,"Symbol":"ALL"},{"Date":"06/01/2021","Transaction":-1,"Value":21962,"Symbol":"HMN"},{"Date":"06/01/2021","Transaction":-1,"Value":49723,"Symbol":"CB"},{"Date":"06/01/2021","Transaction":0,"Value":63030,"Symbol":"L"},{"Date":"06/01/2021","Transaction":0,"Value":63030,"Symbol":"L"},{"Date":"06/01/2021","Transaction":0,"Value":63030,"Symbol":"L"},{"Date":"06/01/2021","Transaction":0,"Value":63030,"Symbol":"L"},{"Date":"06/01/2021","Transaction":0,"Value":63030,"Symbol":"L"},{"Date":"06/01/2021","Transaction":0,"Value":63030,"Symbol":"L"},{"Date":"06/01/2021","Transaction":-1,"Value":25161,"Symbol":"L"},{"Date":"06/01/2021","Transaction":-1,"Value":25148,"Symbol":"L"},{"Date":"06/01/2021","Transaction":-1,"Value":25182,"Symbol":"L"},{"Date":"06/01/2021","Transaction":-1,"Value":25152,"Symbol":"L"},{"Date":"06/01/2021","Transaction":-1,"Value":12616,"Symbol":"L"},{"Date":"06/01/2021","Transaction":-1,"Value":25174,"Symbol":"L"},{"Date":"06/01/2021","Transaction":0,"Value":460642,"Symbol":"THG"},{"Date":"06/01/2021","Transaction":-1,"Value":781069,"Symbol":"THG"},{"Date":"06/01/2021","Transaction":-1,"Value":1320000,"Symbol":"ROOT"},{"Date":"05/31/2021","Transaction":0,"Value":0,"Symbol":"L"},{"Date":"05/28/2021","Transaction":-1,"Value":1805400,"Symbol":"LMND"},{"Date":"05/26/2021","Transaction":1,"Value":4150,"Symbol":"HRTG"},{"Date":"05/21/2021","Transaction":-1,"Value":962122,"Symbol":"ALL"},{"Date":"05/21/2021","Transaction":-1,"Value":274126,"Symbol":"ALL"},{"Date":"05/21/2021","Transaction":-1,"Value":1155000,"Symbol":"SIGI"},{"Date":"05/21/2021","Transaction":0,"Value":3904766,"Symbol":"AFG"},{"Date":"05/21/2021","Transaction":-1,"Value":8268828,"Symbol":"AFG"},{"Date":"05/20/2021","Transaction":-1,"Value":551194,"Symbol":"NMIH"},{"Date":"05/20/2021","Transaction":-1,"Value":4024120,"Symbol":"PGR"},{"Date":"05/20/2021","Transaction":-1,"Value":1190040,"Symbol":"PGR"},{"Date":"05/19/2021","Transaction":-1,"Value":421960,"Symbol":"PLMR"},{"Date":"05/18/2021","Transaction":1,"Value":49140,"Symbol":"UIHC"},{"Date":"05/17/2021","Transaction":0,"Value":1994062,"Symbol":"L"},{"Date":"05/17/2021","Transaction":-1,"Value":645196,"Symbol":"L"},{"Date":"05/17/2021","Transaction":0,"Value":1263000,"Symbol":"AFG"},{"Date":"05/17/2021","Transaction":-1,"Value":2591018,"Symbol":"AFG"},{"Date":"05/17/2021","Transaction":-1,"Value":1345500,"Symbol":"ROOT"},{"Date":"05/14/2021","Transaction":-1,"Value":1210207,"Symbol":"CINF"},{"Date":"05/14/2021","Transaction":0,"Value":80000,"Symbol":"KNSL"},{"Date":"05/14/2021","Transaction":-1,"Value":774900,"Symbol":"KNSL"},{"Date":"05/14/2021","Transaction":1,"Value":8630,"Symbol":"HRTG"},{"Date":"05/14/2021","Transaction":-1,"Value":49266,"Symbol":"NMIH"},{"Date":"05/14/2021","Transaction":0,"Value":1263000,"Symbol":"AFG"},{"Date":"05/14/2021","Transaction":-1,"Value":2596378,"Symbol":"AFG"},{"Date":"05/14/2021","Transaction":-1,"Value":1004894,"Symbol":"AFG"},{"Date":"05/14/2021","Transaction":0,"Value":214675,"Symbol":"THG"},{"Date":"05/14/2021","Transaction":-1,"Value":356403,"Symbol":"THG"},{"Date":"05/13/2021","Transaction":-1,"Value":775898,"Symbol":"KNSL"},{"Date":"05/13/2021","Transaction":-1,"Value":387769,"Symbol":"KNSL"},{"Date":"05/13/2021","Transaction":-1,"Value":413462,"Symbol":"CB"},{"Date":"05/13/2021","Transaction":0,"Value":3453500,"Symbol":"AFG"},{"Date":"05/13/2021","Transaction":-1,"Value":7759200,"Symbol":"AFG"},{"Date":"05/13/2021","Transaction":-1,"Value":128360,"Symbol":"AFG"},{"Date":"05/13/2021","Transaction":0,"Value":1060400,"Symbol":"TRV"},{"Date":"05/13/2021","Transaction":-1,"Value":1564060,"Symbol":"TRV"},{"Date":"05/13/2021","Transaction":-1,"Value":196509,"Symbol":"PLMR"},{"Date":"05/12/2021","Transaction":0,"Value":749995,"Symbol":"CB"},{"Date":"05/12/2021","Transaction":-1,"Value":1702035,"Symbol":"CB"},{"Date":"05/12/2021","Transaction":0,"Value":0,"Symbol":"L"},{"Date":"05/12/2021","Transaction":0,"Value":0,"Symbol":"L"},{"Date":"05/12/2021","Transaction":0,"Value":0,"Symbol":"L"},{"Date":"05/12/2021","Transaction":0,"Value":0,"Symbol":"L"},{"Date":"05/12/2021","Transaction":-1,"Value":97980,"Symbol":"PLMR"},{"Date":"05/10/2021","Transaction":0,"Value":13433783,"Symbol":"ALL"},{"Date":"05/10/2021","Transaction":0,"Value":402800,"Symbol":"ALL"},{"Date":"05/10/2021","Transaction":0,"Value":2857786,"Symbol":"ALL"},{"Date":"05/10/2021","Transaction":-1,"Value":1700797,"Symbol":"ALL"},{"Date":"05/10/2021","Transaction":-1,"Value":20520959,"Symbol":"ALL"},{"Date":"05/10/2021","Transaction":-1,"Value":8472918,"Symbol":"ALL"},{"Date":"05/10/2021","Transaction":-1,"Value":702640,"Symbol":"CB"},{"Date":"05/10/2021","Transaction":0,"Value":4275234,"Symbol":"AFG"},{"Date":"05/10/2021","Transaction":-1,"Value":11207431,"Symbol":"AFG"},{"Date":"05/10/2021","Transaction":0,"Value":636180,"Symbol":"TRV"},{"Date":"05/10/2021","Transaction":-1,"Value":971678,"Symbol":"TRV"},{"Date":"05/10/2021","Transaction":1,"Value":23189,"Symbol":"PLMR"},{"Date":"05/07/2021","Transaction":0,"Value":9332488,"Symbol":"ALL"},{"Date":"05/07/2021","Transaction":-1,"Value":456277,"Symbol":"CNA"},{"Date":"05/07/2021","Transaction":-1,"Value":615230,"Symbol":"KMPR"},{"Date":"05/07/2021","Transaction":0,"Value":88020,"Symbol":"AFG"},{"Date":"05/07/2021","Transaction":-1,"Value":257500,"Symbol":"AFG"},{"Date":"05/07/2021","Transaction":0,"Value":106030,"Symbol":"TRV"},{"Date":"05/07/2021","Transaction":-1,"Value":161000,"Symbol":"TRV"},{"Date":"05/06/2021","Transaction":0,"Value":720012,"Symbol":"KMPR"},{"Date":"05/06/2021","Transaction":0,"Value":4753881,"Symbol":"CB"},{"Date":"05/06/2021","Transaction":-1,"Value":5699436,"Symbol":"CB"},{"Date":"05/06/2021","Transaction":0,"Value":0,"Symbol":"RLI"},{"Date":"05/06/2021","Transaction":0,"Value":0,"Symbol":"RLI"},{"Date":"05/06/2021","Transaction":0,"Value":0,"Symbol":"RLI"},{"Date":"05/06/2021","Transaction":0,"Value":0,"Symbol":"RLI"},{"Date":"05/06/2021","Transaction":0,"Value":0,"Symbol":"RLI"},{"Date":"05/06/2021","Transaction":0,"Value":0,"Symbol":"RLI"},{"Date":"05/06/2021","Transaction":0,"Value":0,"Symbol":"RLI"},{"Date":"05/06/2021","Transaction":0,"Value":0,"Symbol":"RLI"},{"Date":"05/06/2021","Transaction":0,"Value":0,"Symbol":"RLI"},{"Date":"05/06/2021","Transaction":0,"Value":0,"Symbol":"RLI"},{"Date":"05/06/2021","Transaction":0,"Value":342847,"Symbol":"AFG"},{"Date":"05/06/2021","Transaction":-1,"Value":1069789,"Symbol":"AFG"},{"Date":"05/06/2021","Transaction":0,"Value":591426,"Symbol":"TRV"},{"Date":"05/06/2021","Transaction":0,"Value":530150,"Symbol":"TRV"},{"Date":"05/06/2021","Transaction":-1,"Value":801500,"Symbol":"TRV"},{"Date":"05/06/2021","Transaction":-1,"Value":1586911,"Symbol":"TRV"},{"Date":"05/05/2021","Transaction":-1,"Value":126250,"Symbol":"NMIH"},{"Date":"05/05/2021","Transaction":0,"Value":424120,"Symbol":"TRV"},{"Date":"05/05/2021","Transaction":-1,"Value":636500,"Symbol":"TRV"},{"Date":"05/05/2021","Transaction":-1,"Value":392170,"Symbol":"TRV"},{"Date":"05/05/2021","Transaction":0,"Value":0,"Symbol":"UIHC"},{"Date":"05/05/2021","Transaction":0,"Value":0,"Symbol":"UIHC"},{"Date":"05/05/2021","Transaction":0,"Value":0,"Symbol":"UIHC"},{"Date":"05/04/2021","Transaction":0,"Value":159045,"Symbol":"TRV"},{"Date":"05/04/2021","Transaction":0,"Value":4030899,"Symbol":"TRV"},{"Date":"05/04/2021","Transaction":-1,"Value":5998261,"Symbol":"TRV"},{"Date":"05/04/2021","Transaction":-1,"Value":237750,"Symbol":"TRV"},{"Date":"05/04/2021","Transaction":-1,"Value":127376,"Symbol":"PGR"},{"Date":"05/03/2021","Transaction":0,"Value":0,"Symbol":"RLI"},{"Date":"05/03/2021","Transaction":0,"Value":0,"Symbol":"RLI"},{"Date":"05/03/2021","Transaction":0,"Value":0,"Symbol":"RLI"},{"Date":"05/03/2021","Transaction":0,"Value":213946,"Symbol":"THG"},{"Date":"05/03/2021","Transaction":0,"Value":319029,"Symbol":"THG"},{"Date":"05/03/2021","Transaction":0,"Value":220719,"Symbol":"THG"},{"Date":"05/03/2021","Transaction":-1,"Value":399480,"Symbol":"THG"},{"Date":"05/03/2021","Transaction":-1,"Value":649482,"Symbol":"THG"},{"Date":"05/03/2021","Transaction":-1,"Value":379563,"Symbol":"THG"},{"Date":"05/03/2021","Transaction":-1,"Value":286913,"Symbol":"THG"},{"Date":"05/01/2021","Transaction":0,"Value":0,"Symbol":"AXS"},{"Date":"04/30/2021","Transaction":0,"Value":426583,"Symbol":"CINF"},{"Date":"04/30/2021","Transaction":-1,"Value":2448342,"Symbol":"SIGI"},{"Date":"04/26/2021","Transaction":-1,"Value":553,"Symbol":"NMIH"},{"Date":"04/23/2021","Transaction":-1,"Value":882731,"Symbol":"NMIH"},{"Date":"04/23/2021","Transaction":0,"Value":1431405,"Symbol":"TRV"},{"Date":"04/23/2021","Transaction":-1,"Value":2128880,"Symbol":"TRV"},{"Date":"04/22/2021","Transaction":0,"Value":1060300,"Symbol":"TRV"},{"Date":"04/22/2021","Transaction":0,"Value":4899663,"Symbol":"TRV"},{"Date":"04/22/2021","Transaction":-1,"Value":230032,"Symbol":"TRV"},{"Date":"04/22/2021","Transaction":-1,"Value":9451881,"Symbol":"TRV"},{"Date":"04/22/2021","Transaction":-1,"Value":1567680,"Symbol":"TRV"},{"Date":"04/22/2021","Transaction":-1,"Value":43668,"Symbol":"PLMR"},{"Date":"04/21/2021","Transaction":-1,"Value":466985,"Symbol":"PLMR"},{"Date":"04/15/2021","Transaction":-1,"Value":141952,"Symbol":"HMN"},{"Date":"04/15/2021","Transaction":-1,"Value":494120,"Symbol":"LMND"},{"Date":"04/15/2021","Transaction":-1,"Value":1172880,"Symbol":"PGR"},{"Date":"04/13/2021","Transaction":0,"Value":0,"Symbol":"STC"},{"Date":"04/13/2021","Transaction":0,"Value":0,"Symbol":"STC"},{"Date":"04/05/2021","Transaction":-1,"Value":23903,"Symbol":"HMN"},{"Date":"04/05/2021","Transaction":-1,"Value":119204,"Symbol":"PGR"},{"Date":"04/03/2021","Transaction":0,"Value":0,"Symbol":"UIHC"},{"Date":"04/03/2021","Transaction":0,"Value":0,"Symbol":"UIHC"},{"Date":"04/01/2021","Transaction":-1,"Value":855187,"Symbol":"NMIH"},{"Date":"04/01/2021","Transaction":-1,"Value":520714,"Symbol":"PLMR"},{"Date":"03/26/2021","Transaction":1,"Value":252114,"Symbol":"UIHC"},{"Date":"03/26/2021","Transaction":1,"Value":7830,"Symbol":"UIHC"},{"Date":"03/22/2021","Transaction":0,"Value":187500,"Symbol":"PLMR"},{"Date":"03/22/2021","Transaction":-1,"Value":889945,"Symbol":"PLMR"},{"Date":"03/22/2021","Transaction":-1,"Value":42108,"Symbol":"PLMR"},{"Date":"03/19/2021","Transaction":1,"Value":49312,"Symbol":"UIHC"},{"Date":"03/18/2021","Transaction":-1,"Value":75708,"Symbol":"NMIH"},{"Date":"03/18/2021","Transaction":-1,"Value":150540,"Symbol":"AFG"},{"Date":"03/18/2021","Transaction":-1,"Value":1096800,"Symbol":"PGR"},{"Date":"03/17/2021","Transaction":1,"Value":187308,"Symbol":"UIHC"},{"Date":"03/17/2021","Transaction":-1,"Value":459784,"Symbol":"PLMR"},{"Date":"03/16/2021","Transaction":0,"Value":131500,"Symbol":"LMND"},{"Date":"03/16/2021","Transaction":-1,"Value":2670000,"Symbol":"LMND"},{"Date":"03/16/2021","Transaction":0,"Value":832275,"Symbol":"L"},{"Date":"03/16/2021","Transaction":-1,"Value":327447,"Symbol":"L"},{"Date":"03/15/2021","Transaction":-1,"Value":43329,"Symbol":"HMN"},{"Date":"03/15/2021","Transaction":-1,"Value":146319,"Symbol":"HMN"},{"Date":"03/15/2021","Transaction":-1,"Value":583000,"Symbol":"LMND"},{"Date":"03/15/2021","Transaction":0,"Value":375029,"Symbol":"CB"},{"Date":"03/15/2021","Transaction":-1,"Value":759105,"Symbol":"CB"},{"Date":"03/15/2021","Transaction":-1,"Value":133356,"Symbol":"NMIH"},{"Date":"03/15/2021","Transaction":-1,"Value":403975,"Symbol":"ROOT"},{"Date":"03/12/2021","Transaction":0,"Value":215050,"Symbol":"MCY"},{"Date":"03/12/2021","Transaction":0,"Value":835734,"Symbol":"RLI"},{"Date":"03/12/2021","Transaction":0,"Value":1538160,"Symbol":"RLI"},{"Date":"03/12/2021","Transaction":-1,"Value":1724828,"Symbol":"AFG"},{"Date":"03/12/2021","Transaction":-1,"Value":2355710,"Symbol":"ROOT"},{"Date":"03/12/2021","Transaction":0,"Value":1198947,"Symbol":"ARGO"},{"Date":"03/11/2021","Transaction":-1,"Value":423896,"Symbol":"CNA"},{"Date":"03/11/2021","Transaction":0,"Value":1612875,"Symbol":"MCY"},{"Date":"03/11/2021","Transaction":-1,"Value":2212003,"Symbol":"MCY"},{"Date":"03/11/2021","Transaction":0,"Value":386412,"Symbol":"NMIH"},{"Date":"03/11/2021","Transaction":-1,"Value":820234,"Symbol":"NMIH"},{"Date":"03/11/2021","Transaction":-1,"Value":36644,"Symbol":"AFG"},{"Date":"03/10/2021","Transaction":1,"Value":606983,"Symbol":"KNSL"},{"Date":"03/10/2021","Transaction":-1,"Value":724020,"Symbol":"MCY"},{"Date":"03/10/2021","Transaction":-1,"Value":260818,"Symbol":"NMIH"},{"Date":"03/10/2021","Transaction":0,"Value":476364,"Symbol":"RLI"},{"Date":"03/10/2021","Transaction":0,"Value":714150,"Symbol":"RLI"},{"Date":"03/10/2021","Transaction":-1,"Value":121047,"Symbol":"PLMR"},{"Date":"03/08/2021","Transaction":-1,"Value":107712,"Symbol":"SIGI"},{"Date":"03/08/2021","Transaction":0,"Value":528377,"Symbol":"PRA"},{"Date":"03/08/2021","Transaction":0,"Value":76906,"Symbol":"PRA"},{"Date":"03/08/2021","Transaction":0,"Value":51336,"Symbol":"PRA"},{"Date":"03/05/2021","Transaction":0,"Value":80000,"Symbol":"KNSL"},{"Date":"03/05/2021","Transaction":1,"Value":80082,"Symbol":"KNSL"},{"Date":"03/05/2021","Transaction":-1,"Value":782117,"Symbol":"KNSL"},{"Date":"03/04/2021","Transaction":-1,"Value":805172,"Symbol":"KNSL"},{"Date":"03/04/2021","Transaction":-1,"Value":403011,"Symbol":"KNSL"},{"Date":"03/04/2021","Transaction":-1,"Value":110229,"Symbol":"PGR"},{"Date":"03/03/2021","Transaction":0,"Value":9780,"Symbol":"NMIH"},{"Date":"03/03/2021","Transaction":-1,"Value":23966,"Symbol":"NMIH"},{"Date":"03/03/2021","Transaction":0,"Value":95634,"Symbol":"PRA"},{"Date":"03/03/2021","Transaction":0,"Value":63740,"Symbol":"PRA"},{"Date":"03/03/2021","Transaction":0,"Value":30836,"Symbol":"PRA"},{"Date":"03/03/2021","Transaction":0,"Value":95634,"Symbol":"PRA"},{"Date":"03/03/2021","Transaction":0,"Value":95634,"Symbol":"PRA"},{"Date":"03/03/2021","Transaction":0,"Value":30590,"Symbol":"PRA"},{"Date":"03/03/2021","Transaction":0,"Value":142631,"Symbol":"THG"},{"Date":"03/03/2021","Transaction":-1,"Value":241637,"Symbol":"THG"},{"Date":"03/02/2021","Transaction":-1,"Value":615836,"Symbol":"KMPR"},{"Date":"03/02/2021","Transaction":0,"Value":79210,"Symbol":"NMIH"},{"Date":"03/02/2021","Transaction":-1,"Value":194275,"Symbol":"NMIH"},{"Date":"03/02/2021","Transaction":0,"Value":460725,"Symbol":"THG"},{"Date":"03/02/2021","Transaction":-1,"Value":670052,"Symbol":"THG"},{"Date":"03/02/2021","Transaction":-1,"Value":76118,"Symbol":"THG"},{"Date":"03/01/2021","Transaction":-1,"Value":1965240,"Symbol":"ALL"},{"Date":"03/01/2021","Transaction":-1,"Value":881760,"Symbol":"ALL"},{"Date":"03/01/2021","Transaction":0,"Value":0,"Symbol":"AXS"},{"Date":"03/01/2021","Transaction":0,"Value":0,"Symbol":"AXS"},{"Date":"03/01/2021","Transaction":0,"Value":0,"Symbol":"AXS"},{"Date":"03/01/2021","Transaction":0,"Value":0,"Symbol":"AXS"},{"Date":"03/01/2021","Transaction":-1,"Value":386842,"Symbol":"KMPR"},{"Date":"03/01/2021","Transaction":0,"Value":0,"Symbol":"CINF"},{"Date":"03/01/2021","Transaction":0,"Value":0,"Symbol":"CINF"},{"Date":"03/01/2021","Transaction":0,"Value":0,"Symbol":"CINF"},{"Date":"03/01/2021","Transaction":0,"Value":0,"Symbol":"CINF"},{"Date":"03/01/2021","Transaction":0,"Value":0,"Symbol":"CINF"},{"Date":"03/01/2021","Transaction":0,"Value":0,"Symbol":"CINF"},{"Date":"03/01/2021","Transaction":0,"Value":0,"Symbol":"CINF"},{"Date":"03/01/2021","Transaction":0,"Value":0,"Symbol":"CINF"},{"Date":"03/01/2021","Transaction":0,"Value":0,"Symbol":"CINF"},{"Date":"03/01/2021","Transaction":0,"Value":0,"Symbol":"CINF"},{"Date":"03/01/2021","Transaction":0,"Value":0,"Symbol":"CINF"},{"Date":"03/01/2021","Transaction":0,"Value":0,"Symbol":"CINF"},{"Date":"03/01/2021","Transaction":0,"Value":0,"Symbol":"CINF"},{"Date":"03/01/2021","Transaction":0,"Value":539450,"Symbol":"LMND"},{"Date":"03/01/2021","Transaction":-1,"Value":6395000,"Symbol":"LMND"},{"Date":"03/01/2021","Transaction":0,"Value":64710,"Symbol":"L"},{"Date":"03/01/2021","Transaction":0,"Value":64710,"Symbol":"L"},{"Date":"03/01/2021","Transaction":0,"Value":64710,"Symbol":"L"},{"Date":"03/01/2021","Transaction":0,"Value":64710,"Symbol":"L"},{"Date":"03/01/2021","Transaction":0,"Value":64710,"Symbol":"L"},{"Date":"03/01/2021","Transaction":0,"Value":64710,"Symbol":"L"},{"Date":"03/01/2021","Transaction":-1,"Value":8400,"Symbol":"L"},{"Date":"03/01/2021","Transaction":-1,"Value":8383,"Symbol":"L"},{"Date":"03/01/2021","Transaction":-1,"Value":8384,"Symbol":"L"},{"Date":"03/01/2021","Transaction":-1,"Value":8391,"Symbol":"L"},{"Date":"03/01/2021","Transaction":-1,"Value":4196,"Symbol":"L"},{"Date":"03/01/2021","Transaction":-1,"Value":8391,"Symbol":"L"},{"Date":"03/01/2021","Transaction":-1,"Value":1743683,"Symbol":"NMIH"},{"Date":"02/25/2021","Transaction":0,"Value":154717,"Symbol":"CINF"},{"Date":"02/25/2021","Transaction":-1,"Value":133320,"Symbol":"HMN"},{"Date":"02/25/2021","Transaction":-1,"Value":299160,"Symbol":"TRV"},{"Date":"02/24/2021","Transaction":0,"Value":86615,"Symbol":"STFC"},{"Date":"02/24/2021","Transaction":-1,"Value":92158,"Symbol":"STFC"},{"Date":"02/24/2021","Transaction":-1,"Value":893840,"Symbol":"NMIH"},{"Date":"02/24/2021","Transaction":0,"Value":597400,"Symbol":"TRV"},{"Date":"02/24/2021","Transaction":0,"Value":477135,"Symbol":"TRV"},{"Date":"02/24/2021","Transaction":-1,"Value":677250,"Symbol":"TRV"},{"Date":"02/24/2021","Transaction":-1,"Value":1506270,"Symbol":"TRV"},{"Date":"02/23/2021","Transaction":0,"Value":19346,"Symbol":"STFC"},{"Date":"02/23/2021","Transaction":-1,"Value":1006530,"Symbol":"CB"},{"Date":"02/23/2021","Transaction":0,"Value":557709,"Symbol":"TRV"},{"Date":"02/23/2021","Transaction":0,"Value":318090,"Symbol":"TRV"},{"Date":"02/23/2021","Transaction":-1,"Value":448305,"Symbol":"TRV"},{"Date":"02/23/2021","Transaction":-1,"Value":1717274,"Symbol":"TRV"},{"Date":"02/23/2021","Transaction":0,"Value":187500,"Symbol":"PLMR"},{"Date":"02/23/2021","Transaction":-1,"Value":1087935,"Symbol":"PLMR"},{"Date":"02/22/2021","Transaction":0,"Value":56117,"Symbol":"CINF"},{"Date":"02/22/2021","Transaction":-1,"Value":58848,"Symbol":"PLMR"},{"Date":"02/19/2021","Transaction":0,"Value":0,"Symbol":"ALL"},{"Date":"02/19/2021","Transaction":0,"Value":0,"Symbol":"ALL"},{"Date":"02/19/2021","Transaction":0,"Value":215050,"Symbol":"MCY"},{"Date":"02/17/2021","Transaction":0,"Value":318090,"Symbol":"TRV"},{"Date":"02/17/2021","Transaction":-1,"Value":444750,"Symbol":"TRV"},{"Date":"02/17/2021","Transaction":-1,"Value":664042,"Symbol":"PLMR"},{"Date":"02/16/2021","Transaction":0,"Value":0,"Symbol":"CINF"},{"Date":"02/16/2021","Transaction":0,"Value":0,"Symbol":"CINF"},{"Date":"02/16/2021","Transaction":-1,"Value":136080,"Symbol":"HMN"},{"Date":"02/16/2021","Transaction":-1,"Value":911515,"Symbol":"LMND"},{"Date":"02/12/2021","Transaction":1,"Value":38000,"Symbol":"KMPR"},{"Date":"02/12/2021","Transaction":1,"Value":35083,"Symbol":"CINF"},{"Date":"02/12/2021","Transaction":0,"Value":0,"Symbol":"L"},{"Date":"02/12/2021","Transaction":0,"Value":0,"Symbol":"L"},{"Date":"02/12/2021","Transaction":0,"Value":0,"Symbol":"L"},{"Date":"02/12/2021","Transaction":0,"Value":0,"Symbol":"L"},{"Date":"02/12/2021","Transaction":0,"Value":0,"Symbol":"L"},{"Date":"02/12/2021","Transaction":0,"Value":0,"Symbol":"L"},{"Date":"02/12/2021","Transaction":-1,"Value":216031,"Symbol":"L"},{"Date":"02/11/2021","Transaction":0,"Value":0,"Symbol":"L"},{"Date":"02/11/2021","Transaction":0,"Value":0,"Symbol":"L"},{"Date":"02/11/2021","Transaction":0,"Value":0,"Symbol":"L"},{"Date":"02/11/2021","Transaction":0,"Value":0,"Symbol":"L"},{"Date":"02/11/2021","Transaction":0,"Value":0,"Symbol":"L"},{"Date":"02/11/2021","Transaction":0,"Value":0,"Symbol":"L"},{"Date":"02/11/2021","Transaction":-1,"Value":210520,"Symbol":"L"},{"Date":"02/10/2021","Transaction":-1,"Value":165360,"Symbol":"CB"},{"Date":"02/10/2021","Transaction":0,"Value":1866530,"Symbol":"TRV"},{"Date":"02/10/2021","Transaction":-1,"Value":3397388,"Symbol":"TRV"},{"Date":"02/08/2021","Transaction":0,"Value":64000,"Symbol":"KNSL"},{"Date":"02/08/2021","Transaction":-1,"Value":758090,"Symbol":"KNSL"},{"Date":"02/08/2021","Transaction":0,"Value":99973,"Symbol":"CB"},{"Date":"02/08/2021","Transaction":-1,"Value":924280,"Symbol":"CB"},{"Date":"02/05/2021","Transaction":-1,"Value":10708630,"Symbol":"ALL"},{"Date":"02/05/2021","Transaction":-1,"Value":82510,"Symbol":"CB"},{"Date":"02/05/2021","Transaction":1,"Value":240975,"Symbol":"AFG"},{"Date":"02/04/2021","Transaction":1,"Value":140232,"Symbol":"KMPR"},{"Date":"02/04/2021","Transaction":-1,"Value":1000375,"Symbol":"CB"},{"Date":"02/04/2021","Transaction":-1,"Value":108079,"Symbol":"PGR"},{"Date":"02/03/2021","Transaction":0,"Value":187500,"Symbol":"PLMR"},{"Date":"02/03/2021","Transaction":-1,"Value":165039,"Symbol":"PLMR"},{"Date":"02/03/2021","Transaction":-1,"Value":1374539,"Symbol":"PLMR"},{"Date":"02/03/2021","Transaction":-1,"Value":202586,"Symbol":"PGR"},{"Date":"02/01/2021","Transaction":-1,"Value":794099,"Symbol":"NMIH"},{"Date":"01/26/2021","Transaction":0,"Value":318090,"Symbol":"TRV"},{"Date":"01/26/2021","Transaction":-1,"Value":441750,"Symbol":"TRV"},{"Date":"01/25/2021","Transaction":0,"Value":424120,"Symbol":"TRV"},{"Date":"01/25/2021","Transaction":0,"Value":4187798,"Symbol":"TRV"},{"Date":"01/25/2021","Transaction":-1,"Value":7779347,"Symbol":"TRV"},{"Date":"01/25/2021","Transaction":-1,"Value":585000,"Symbol":"TRV"},{"Date":"01/22/2021","Transaction":-1,"Value":58056,"Symbol":"PLMR"},{"Date":"01/21/2021","Transaction":0,"Value":187500,"Symbol":"PLMR"},{"Date":"01/21/2021","Transaction":-1,"Value":1217486,"Symbol":"PLMR"},{"Date":"01/20/2021","Transaction":-1,"Value":445500,"Symbol":"LMND"},{"Date":"01/20/2021","Transaction":-1,"Value":620248,"Symbol":"PLMR"},{"Date":"01/19/2021","Transaction":-1,"Value":82198314,"Symbol":"LMND"},{"Date":"01/19/2021","Transaction":-1,"Value":15943130,"Symbol":"LMND"},{"Date":"01/19/2021","Transaction":-1,"Value":7971565,"Symbol":"LMND"},{"Date":"01/19/2021","Transaction":-1,"Value":47829390,"Symbol":"LMND"},{"Date":"01/15/2021","Transaction":-1,"Value":147525,"Symbol":"HMN"},{"Date":"01/15/2021","Transaction":-1,"Value":140528,"Symbol":"HMN"},{"Date":"01/15/2021","Transaction":-1,"Value":9432802,"Symbol":"LMND"},{"Date":"01/12/2021","Transaction":-1,"Value":990801,"Symbol":"PLMR"},{"Date":"01/11/2021","Transaction":-1,"Value":272874,"Symbol":"PLMR"},{"Date":"01/08/2021","Transaction":-1,"Value":40138,"Symbol":"PLMR"},{"Date":"01/07/2021","Transaction":0,"Value":210348,"Symbol":"NMIH"},{"Date":"01/07/2021","Transaction":-1,"Value":453536,"Symbol":"NMIH"},{"Date":"01/06/2021","Transaction":0,"Value":65177,"Symbol":"NMIH"},{"Date":"01/06/2021","Transaction":-1,"Value":431261,"Symbol":"NMIH"},{"Date":"01/06/2021","Transaction":-1,"Value":132240,"Symbol":"PLMR"},{"Date":"01/05/2021","Transaction":0,"Value":1800112,"Symbol":"L"},{"Date":"01/05/2021","Transaction":-1,"Value":205396,"Symbol":"L"},{"Date":"01/05/2021","Transaction":-1,"Value":329250,"Symbol":"PGR"},{"Date":"01/05/2021","Transaction":-1,"Value":573727,"Symbol":"PGR"},{"Date":"01/05/2021","Transaction":-1,"Value":642227,"Symbol":"PGR"},{"Date":"01/05/2021","Transaction":-1,"Value":121118,"Symbol":"PGR"},{"Date":"01/04/2021","Transaction":0,"Value":0,"Symbol":"ALL"},{"Date":"01/04/2021","Transaction":-1,"Value":22912,"Symbol":"HMN"},{"Date":"01/04/2021","Transaction":0,"Value":2400150,"Symbol":"L"},{"Date":"01/04/2021","Transaction":-1,"Value":298348,"Symbol":"L"},{"Date":"01/04/2021","Transaction":0,"Value":430379,"Symbol":"NMIH"},{"Date":"01/04/2021","Transaction":-1,"Value":802941,"Symbol":"NMIH"},{"Date":"01/04/2021","Transaction":-1,"Value":140222,"Symbol":"RLI"},{"Date":"01/04/2021","Transaction":-1,"Value":656432,"Symbol":"PLMR"},{"Date":"01/01/2021","Transaction":0,"Value":0,"Symbol":"ALL"},{"Date":"01/01/2021","Transaction":0,"Value":0,"Symbol":"PGR"},{"Date":"01/01/2021","Transaction":0,"Value":0,"Symbol":"PGR"},{"Date":"01/01/2021","Transaction":0,"Value":0,"Symbol":"PGR"},{"Date":"01/01/2021","Transaction":0,"Value":0,"Symbol":"PGR"},{"Date":"01/01/2021","Transaction":0,"Value":0,"Symbol":"PGR"},{"Date":"01/01/2021","Transaction":0,"Value":0,"Symbol":"PGR"},{"Date":"01/01/2021","Transaction":0,"Value":0,"Symbol":"PGR"},{"Date":"01/01/2021","Transaction":0,"Value":0,"Symbol":"PGR"},{"Date":"01/01/2021","Transaction":0,"Value":0,"Symbol":"PGR"},{"Date":"01/01/2021","Transaction":0,"Value":0,"Symbol":"PGR"},{"Date":"01/01/2021","Transaction":0,"Value":0,"Symbol":"PGR"},{"Date":"01/01/2021","Transaction":0,"Value":0,"Symbol":"PGR"},{"Date":"01/01/2021","Transaction":0,"Value":0,"Symbol":"PGR"},{"Date":"12/30/2020","Transaction":1,"Value":12477184,"Symbol":"ROOT"},{"Date":"12/28/2020","Transaction":-1,"Value":592450,"Symbol":"LMND"},{"Date":"12/28/2020","Transaction":1,"Value":59500,"Symbol":"UIHC"},{"Date":"12/24/2020","Transaction":-1,"Value":3244431,"Symbol":"LMND"},{"Date":"12/24/2020","Transaction":1,"Value":122200,"Symbol":"UIHC"},{"Date":"12/23/2020","Transaction":-1,"Value":25941726,"Symbol":"LMND"},{"Date":"12/23/2020","Transaction":1,"Value":38880,"Symbol":"UIHC"},{"Date":"12/23/2020","Transaction":-1,"Value":593039,"Symbol":"PLMR"},{"Date":"12/22/2020","Transaction":-1,"Value":13960029,"Symbol":"LMND"},{"Date":"12/22/2020","Transaction":1,"Value":51995,"Symbol":"UIHC"},{"Date":"12/22/2020","Transaction":1,"Value":82240,"Symbol":"UIHC"},{"Date":"12/22/2020","Transaction":-1,"Value":52914,"Symbol":"PLMR"},{"Date":"12/21/2020","Transaction":-1,"Value":7517885,"Symbol":"LMND"},{"Date":"12/21/2020","Transaction":1,"Value":6364,"Symbol":"UIHC"},{"Date":"12/21/2020","Transaction":1,"Value":41246,"Symbol":"UIHC"},{"Date":"12/21/2020","Transaction":1,"Value":25950,"Symbol":"UIHC"},{"Date":"12/21/2020","Transaction":1,"Value":48786,"Symbol":"UIHC"},{"Date":"12/21/2020","Transaction":-1,"Value":319392,"Symbol":"PGR"},{"Date":"12/18/2020","Transaction":-1,"Value":1105021,"Symbol":"PLMR"},{"Date":"12/17/2020","Transaction":-1,"Value":918468,"Symbol":"LMND"},{"Date":"12/17/2020","Transaction":0,"Value":647100,"Symbol":"L"},{"Date":"12/17/2020","Transaction":0,"Value":647100,"Symbol":"L"},{"Date":"12/17/2020","Transaction":-1,"Value":1409496,"Symbol":"PGR"},{"Date":"12/17/2020","Transaction":-1,"Value":1274655,"Symbol":"PGR"},{"Date":"12/15/2020","Transaction":-1,"Value":149975,"Symbol":"HMN"},{"Date":"12/15/2020","Transaction":-1,"Value":142862,"Symbol":"HMN"},{"Date":"12/15/2020","Transaction":-1,"Value":1206873,"Symbol":"KNSL"},{"Date":"12/15/2020","Transaction":0,"Value":1718737,"Symbol":"CB"},{"Date":"12/15/2020","Transaction":-1,"Value":3586060,"Symbol":"CB"},{"Date":"12/15/2020","Transaction":0,"Value":96583,"Symbol":"AFG"},{"Date":"12/15/2020","Transaction":0,"Value":264850,"Symbol":"PLMR"},{"Date":"12/15/2020","Transaction":-1,"Value":401850,"Symbol":"PLMR"},{"Date":"12/15/2020","Transaction":-1,"Value":255447,"Symbol":"PGR"},{"Date":"12/14/2020","Transaction":-1,"Value":72147,"Symbol":"KNSL"},{"Date":"12/14/2020","Transaction":-1,"Value":377780,"Symbol":"LMND"},{"Date":"12/11/2020","Transaction":1,"Value":293727,"Symbol":"STFC"},{"Date":"12/11/2020","Transaction":-1,"Value":11294,"Symbol":"LMND"},{"Date":"12/11/2020","Transaction":-1,"Value":578909,"Symbol":"LMND"},{"Date":"12/10/2020","Transaction":1,"Value":3733,"Symbol":"STFC"},{"Date":"12/10/2020","Transaction":-1,"Value":518550,"Symbol":"LMND"},{"Date":"12/10/2020","Transaction":-1,"Value":11457216,"Symbol":"LMND"},{"Date":"12/10/2020","Transaction":0,"Value":1753050,"Symbol":"L"},{"Date":"12/10/2020","Transaction":0,"Value":1753050,"Symbol":"L"},{"Date":"12/10/2020","Transaction":0,"Value":310944,"Symbol":"NMIH"},{"Date":"12/10/2020","Transaction":-1,"Value":471830,"Symbol":"NMIH"},{"Date":"12/09/2020","Transaction":1,"Value":337920,"Symbol":"STFC"},{"Date":"12/09/2020","Transaction":0,"Value":430379,"Symbol":"NMIH"},{"Date":"12/09/2020","Transaction":-1,"Value":893577,"Symbol":"NMIH"},{"Date":"12/08/2020","Transaction":-1,"Value":549358,"Symbol":"KNSL"},{"Date":"12/08/2020","Transaction":-1,"Value":20089055,"Symbol":"LMND"},{"Date":"12/08/2020","Transaction":-1,"Value":1482696,"Symbol":"LMND"},{"Date":"12/07/2020","Transaction":-1,"Value":380148,"Symbol":"LMND"},{"Date":"12/07/2020","Transaction":-1,"Value":90165,"Symbol":"LMND"},{"Date":"12/07/2020","Transaction":0,"Value":1479040,"Symbol":"CB"},{"Date":"12/07/2020","Transaction":-1,"Value":2640586,"Symbol":"CB"},{"Date":"12/04/2020","Transaction":-1,"Value":530270,"Symbol":"LMND"},{"Date":"12/03/2020","Transaction":0,"Value":136705,"Symbol":"CINF"},{"Date":"12/03/2020","Transaction":0,"Value":64000,"Symbol":"KNSL"},{"Date":"12/03/2020","Transaction":-1,"Value":951052,"Symbol":"KNSL"},{"Date":"12/03/2020","Transaction":-1,"Value":674250,"Symbol":"LMND"},{"Date":"12/03/2020","Transaction":-1,"Value":1473100,"Symbol":"LMND"},{"Date":"12/03/2020","Transaction":-1,"Value":1440000,"Symbol":"LMND"},{"Date":"12/03/2020","Transaction":-1,"Value":8811741,"Symbol":"LMND"},{"Date":"12/03/2020","Transaction":1,"Value":50250,"Symbol":"PLMR"},{"Date":"12/02/2020","Transaction":1,"Value":79700,"Symbol":"STFC"},{"Date":"12/02/2020","Transaction":-1,"Value":19802,"Symbol":"LMND"},{"Date":"12/02/2020","Transaction":0,"Value":179942,"Symbol":"AFG"},{"Date":"12/02/2020","Transaction":-1,"Value":102795,"Symbol":"PLMR"},{"Date":"12/01/2020","Transaction":0,"Value":0,"Symbol":"AXS"},{"Date":"12/01/2020","Transaction":-1,"Value":1314471,"Symbol":"LMND"},{"Date":"12/01/2020","Transaction":-1,"Value":3684983,"Symbol":"LMND"},{"Date":"12/01/2020","Transaction":-1,"Value":1908422,"Symbol":"LMND"},{"Date":"12/01/2020","Transaction":0,"Value":58485,"Symbol":"L"},{"Date":"12/01/2020","Transaction":0,"Value":58485,"Symbol":"L"},{"Date":"12/01/2020","Transaction":0,"Value":58485,"Symbol":"L"},{"Date":"12/01/2020","Transaction":0,"Value":58485,"Symbol":"L"},{"Date":"12/01/2020","Transaction":0,"Value":58485,"Symbol":"L"},{"Date":"12/01/2020","Transaction":-1,"Value":5985,"Symbol":"L"},{"Date":"12/01/2020","Transaction":-1,"Value":5985,"Symbol":"L"},{"Date":"12/01/2020","Transaction":-1,"Value":5985,"Symbol":"L"},{"Date":"12/01/2020","Transaction":-1,"Value":5984,"Symbol":"L"},{"Date":"12/01/2020","Transaction":-1,"Value":3013,"Symbol":"L"},{"Date":"12/01/2020","Transaction":-1,"Value":514625,"Symbol":"PGR"},{"Date":"11/30/2020","Transaction":1,"Value":118737,"Symbol":"STFC"},{"Date":"11/30/2020","Transaction":0,"Value":451257,"Symbol":"NMIH"},{"Date":"11/30/2020","Transaction":-1,"Value":805604,"Symbol":"NMIH"},{"Date":"11/30/2020","Transaction":1,"Value":5849,"Symbol":"UIHC"},{"Date":"11/27/2020","Transaction":1,"Value":10629,"Symbol":"STFC"},{"Date":"11/27/2020","Transaction":-1,"Value":559226,"Symbol":"LMND"},{"Date":"11/25/2020","Transaction":0,"Value":2672,"Symbol":"CINF"},{"Date":"11/25/2020","Transaction":-1,"Value":7220,"Symbol":"LMND"},{"Date":"11/24/2020","Transaction":-1,"Value":690370,"Symbol":"LMND"},{"Date":"11/24/2020","Transaction":0,"Value":248022,"Symbol":"NMIH"},{"Date":"11/24/2020","Transaction":-1,"Value":1293314,"Symbol":"NMIH"},{"Date":"11/24/2020","Transaction":-1,"Value":182542,"Symbol":"NMIH"},{"Date":"11/23/2020","Transaction":0,"Value":0,"Symbol":"CINF"},{"Date":"11/23/2020","Transaction":-1,"Value":874734,"Symbol":"PLMR"},{"Date":"11/23/2020","Transaction":-1,"Value":42126,"Symbol":"PLMR"},{"Date":"11/20/2020","Transaction":1,"Value":11636,"Symbol":"STFC"},{"Date":"11/20/2020","Transaction":-1,"Value":352725,"Symbol":"PLMR"},{"Date":"11/20/2020","Transaction":-1,"Value":311094,"Symbol":"PGR"},{"Date":"11/19/2020","Transaction":1,"Value":37576,"Symbol":"STFC"},{"Date":"11/19/2020","Transaction":0,"Value":378130,"Symbol":"NMIH"},{"Date":"11/19/2020","Transaction":-1,"Value":730227,"Symbol":"NMIH"},{"Date":"11/19/2020","Transaction":-1,"Value":3157650,"Symbol":"PGR"},{"Date":"11/18/2020","Transaction":-1,"Value":90274,"Symbol":"NMIH"},{"Date":"11/18/2020","Transaction":0,"Value":265075,"Symbol":"TRV"},{"Date":"11/18/2020","Transaction":-1,"Value":342500,"Symbol":"TRV"},{"Date":"11/17/2020","Transaction":-1,"Value":100000,"Symbol":"HMN"},{"Date":"11/17/2020","Transaction":-1,"Value":1288232,"Symbol":"LMND"},{"Date":"11/17/2020","Transaction":-1,"Value":2241984,"Symbol":"LMND"},{"Date":"11/17/2020","Transaction":-1,"Value":630774,"Symbol":"SIGI"},{"Date":"11/17/2020","Transaction":-1,"Value":176250,"Symbol":"NMIH"},{"Date":"11/17/2020","Transaction":-1,"Value":1070213,"Symbol":"PLMR"},{"Date":"11/16/2020","Transaction":1,"Value":199206,"Symbol":"CINF"},{"Date":"11/16/2020","Transaction":-1,"Value":100000,"Symbol":"HMN"},{"Date":"11/16/2020","Transaction":-1,"Value":140315,"Symbol":"HMN"},{"Date":"11/16/2020","Transaction":-1,"Value":133660,"Symbol":"HMN"},{"Date":"11/16/2020","Transaction":-1,"Value":143973,"Symbol":"CB"},{"Date":"11/16/2020","Transaction":0,"Value":819080,"Symbol":"NMIH"},{"Date":"11/16/2020","Transaction":0,"Value":430379,"Symbol":"NMIH"},{"Date":"11/16/2020","Transaction":-1,"Value":861564,"Symbol":"NMIH"},{"Date":"11/16/2020","Transaction":-1,"Value":1739084,"Symbol":"NMIH"},{"Date":"11/16/2020","Transaction":0,"Value":589063,"Symbol":"RLI"},{"Date":"11/16/2020","Transaction":0,"Value":530150,"Symbol":"TRV"},{"Date":"11/16/2020","Transaction":-1,"Value":681056,"Symbol":"TRV"}]